{
  "stable": true,
  "versions": {
    "1.0.0": {
      "manifest": {
        "id": "io.github.bstrana.diamond-manager-scorer",
        "title": "Diamond Manager Scorer",
        "author": "bstrana",
        "description": "Live baseball scoring app with real-time scoreboard overlay for streaming. Tracks teams, rosters, score, counts, and game progress, and logs each plate appearance.",
        "tagline": "Live baseball scoring and streaming overlay",
        "version": "1.0.0",
        "manifestVersion": 2,
        "minBoxVersion": "9.1.0",
        "website": "https://github.com/bstrana/diamond-manager-scorer",
        "contactEmail": "support@example.com",
        "healthCheckPath": "/health",
        "httpPort": 8000,
        "dockerImage": "ghcr.io/bstrana/diamond-manager-scorer:1.0.0",
        "addons": { "localstorage": {} },
        "icon": "file://appicon.png",
        "iconUrl": "https://bstrana.sirv.com/ybc/ybc-logo.png",
        "tags": ["sports", "baseball", "scoring", "obs", "streaming"],
        "mediaLinks": [
          "https://raw.githubusercontent.com/bstrana/diamond-scheduler/main/public/logo.png"
        ],
        "changelog": "Initial Cloudron release with embedded PocketBase backend.",
        "packagerName": "bstrana",
        "packagerUrl": "https://github.com/bstrana"
      },
      "creationDate": "Mon, 30 Mar 2026 00:00:00 GMT",
      "ts": "Mon, 30 Mar 2026 00:00:00 GMT",
      "publishState": "published"
    },
    "1.0.1": {
      "manifest": {
        "id": "io.github.bstrana.diamond-manager-scorer",
        "title": "Diamond Manager Scorer",
        "author": "bstrana",
        "description": "Live baseball scoring app with real-time scoreboard overlay for streaming. Tracks teams, rosters, score, counts, and game progress, and logs each plate appearance.",
        "tagline": "Live baseball scoring and streaming overlay",
        "version": "1.0.1",
        "manifestVersion": 2,
        "minBoxVersion": "9.1.0",
        "website": "https://github.com/bstrana/diamond-manager-scorer",
        "contactEmail": "support@example.com",
        "healthCheckPath": "/health",
        "httpPort": 8000,
        "dockerImage": "ghcr.io/bstrana/diamond-manager-scorer:1.0.1",
        "addons": { "localstorage": {} },
        "icon": "file://appicon.png",
        "iconUrl": "https://bstrana.sirv.com/ybc/ybc-logo.png",
        "tags": ["sports", "baseball", "scoring", "obs", "streaming"],
        "mediaLinks": [
          "https://raw.githubusercontent.com/bstrana/diamond-scheduler/main/public/logo.png"
        ],
        "changelog": "Add SCHEDULER_URL and SCHEDULER_ORG_ID env vars to connect to a separate Diamond Manager Scheduler app.",
        "packagerName": "bstrana",
        "packagerUrl": "https://github.com/bstrana"
      },
      "creationDate": "Mon, 31 Mar 2026 00:00:00 GMT",
      "ts": "Mon, 31 Mar 2026 00:00:00 GMT",
      "publishState": "published"
    },
    "1.0.2": {
      "manifest": {
        "id": "io.github.bstrana.diamond-manager-scorer",
        "title": "Diamond Manager Scorer",
        "author": "bstrana",
        "description": "Live baseball scoring app with real-time scoreboard overlay for streaming. Tracks teams, rosters, score, counts, and game progress, and logs each plate appearance.",
        "tagline": "Live baseball scoring and streaming overlay",
        "version": "1.0.2",
        "manifestVersion": 2,
        "minBoxVersion": "9.1.0",
        "website": "https://github.com/bstrana/diamond-manager-scorer",
        "contactEmail": "support@example.com",
        "healthCheckPath": "/health",
        "httpPort": 8000,
        "dockerImage": "ghcr.io/bstrana/diamond-manager-scorer:1.0.2",
        "addons": { "localstorage": {} },
        "icon": "file://appicon.png",
        "iconUrl": "https://bstrana.sirv.com/ybc/ybc-logo.png",
        "tags": ["sports", "baseball", "scoring", "obs", "streaming"],
        "mediaLinks": [
          "https://raw.githubusercontent.com/bstrana/diamond-scheduler/main/public/logo.png"
        ],
        "changelog": "Patch release: version bump.",
        "packagerName": "bstrana",
        "packagerUrl": "https://github.com/bstrana"
      },
      "creationDate": "Mon, 31 Mar 2026 00:00:00 GMT",
      "ts": "Mon, 31 Mar 2026 00:00:00 GMT",
      "publishState": "published"
    },
    "1.0.6": {
      "manifest": {
        "id": "io.github.bstrana.diamond-manager-scorer",
        "title": "Diamond Manager Scorer",
        "author": "bstrana",
        "description": "Live baseball scoring app with real-time scoreboard overlay for streaming. Tracks teams, rosters, score, counts, and game progress, and logs each plate appearance.",
        "tagline": "Live baseball scoring and streaming overlay",
        "version": "1.0.6",
        "manifestVersion": 2,
        "minBoxVersion": "9.1.0",
        "website": "https://github.com/bstrana/diamond-manager-scorer",
        "contactEmail": "support@example.com",
        "healthCheckPath": "/health",
        "httpPort": 8000,
        "dockerImage": "ghcr.io/bstrana/diamond-manager-scorer:1.0.6",
        "addons": { "localstorage": {} },
        "icon": "file://appicon.png",
        "iconUrl": "https://bstrana.sirv.com/ybc/ybc-logo.png",
        "tags": ["sports", "baseball", "scoring", "obs", "streaming"],
        "mediaLinks": [
          "https://raw.githubusercontent.com/bstrana/diamond-scheduler/main/public/logo.png"
        ],
        "changelog": "Filter schedule list by logged-in user's org_id; client-side fallback handles alternate field names.",
        "packagerName": "bstrana",
        "packagerUrl": "https://github.com/bstrana"
      },
      "creationDate": "Mon, 31 Mar 2026 20:00:00 GMT",
      "ts": "Mon, 31 Mar 2026 20:00:00 GMT",
      "publishState": "published"
    },
    "1.0.5": {
      "manifest": {
        "id": "io.github.bstrana.diamond-manager-scorer",
        "title": "Diamond Manager Scorer",
        "author": "bstrana",
        "description": "Live baseball scoring app with real-time scoreboard overlay for streaming. Tracks teams, rosters, score, counts, and game progress, and logs each plate appearance.",
        "tagline": "Live baseball scoring and streaming overlay",
        "version": "1.0.5",
        "manifestVersion": 2,
        "minBoxVersion": "9.1.0",
        "website": "https://github.com/bstrana/diamond-manager-scorer",
        "contactEmail": "support@example.com",
        "healthCheckPath": "/health",
        "httpPort": 8000,
        "dockerImage": "ghcr.io/bstrana/diamond-manager-scorer:1.0.5",
        "addons": { "localstorage": {} },
        "icon": "file://appicon.png",
        "iconUrl": "https://bstrana.sirv.com/ybc/ybc-logo.png",
        "tags": ["sports", "baseball", "scoring", "obs", "streaming"],
        "mediaLinks": [
          "https://raw.githubusercontent.com/bstrana/diamond-scheduler/main/public/logo.png"
        ],
        "changelog": "Remove sort=-updated from schedule list query; fixes 400 Bad Request from external scheduler collections.",
        "packagerName": "bstrana",
        "packagerUrl": "https://github.com/bstrana"
      },
      "creationDate": "Mon, 31 Mar 2026 19:00:00 GMT",
      "ts": "Mon, 31 Mar 2026 19:00:00 GMT",
      "publishState": "published"
    },
    "1.0.4": {
      "manifest": {
        "id": "io.github.bstrana.diamond-manager-scorer",
        "title": "Diamond Manager Scorer",
        "author": "bstrana",
        "description": "Live baseball scoring app with real-time scoreboard overlay for streaming. Tracks teams, rosters, score, counts, and game progress, and logs each plate appearance.",
        "tagline": "Live baseball scoring and streaming overlay",
        "version": "1.0.4",
        "manifestVersion": 2,
        "minBoxVersion": "9.1.0",
        "website": "https://github.com/bstrana/diamond-manager-scorer",
        "contactEmail": "support@example.com",
        "healthCheckPath": "/health",
        "httpPort": 8000,
        "dockerImage": "ghcr.io/bstrana/diamond-manager-scorer:1.0.4",
        "addons": { "localstorage": {} },
        "icon": "file://appicon.png",
        "iconUrl": "https://bstrana.sirv.com/ybc/ybc-logo.png",
        "tags": ["sports", "baseball", "scoring", "obs", "streaming"],
        "mediaLinks": [
          "https://raw.githubusercontent.com/bstrana/diamond-scheduler/main/public/logo.png"
        ],
        "changelog": "Fix scheduler proxy: re-append /_pb path segment so PocketBase API requests route correctly.",
        "packagerName": "bstrana",
        "packagerUrl": "https://github.com/bstrana"
      },
      "creationDate": "Mon, 31 Mar 2026 18:00:00 GMT",
      "ts": "Mon, 31 Mar 2026 18:00:00 GMT",
      "publishState": "published"
    },
    "1.0.3": {
      "manifest": {
        "id": "io.github.bstrana.diamond-manager-scorer",
        "title": "Diamond Manager Scorer",
        "author": "bstrana",
        "description": "Live baseball scoring app with real-time scoreboard overlay for streaming. Tracks teams, rosters, score, counts, and game progress, and logs each plate appearance.",
        "tagline": "Live baseball scoring and streaming overlay",
        "version": "1.0.3",
        "manifestVersion": 2,
        "minBoxVersion": "9.1.0",
        "website": "https://github.com/bstrana/diamond-manager-scorer",
        "contactEmail": "support@example.com",
        "healthCheckPath": "/health",
        "httpPort": 8000,
        "dockerImage": "ghcr.io/bstrana/diamond-manager-scorer:1.0.3",
        "addons": { "localstorage": {} },
        "icon": "file://appicon.png",
        "iconUrl": "https://bstrana.sirv.com/ybc/ybc-logo.png",
        "tags": ["sports", "baseball", "scoring", "obs", "streaming"],
        "mediaLinks": [
          "https://raw.githubusercontent.com/bstrana/diamond-scheduler/main/public/logo.png"
        ],
        "changelog": "Fix CORS/ERR_NAME_NOT_RESOLVED on schedule fetch; add SCHEDULER_COLLECTION env var (default: published_schedules).",
        "packagerName": "bstrana",
        "packagerUrl": "https://github.com/bstrana"
      },
      "creationDate": "Mon, 31 Mar 2026 12:00:00 GMT",
      "ts": "Mon, 31 Mar 2026 12:00:00 GMT",
      "publishState": "published"
    }
  }
}
